perceptual_load/__init__.py
perceptual_load/perceptual_load_experiment.py
perceptual_load/distractors/Donaldduck.jpeg
perceptual_load/distractors/Mickeymouse.jpeg
perceptual_load/distractors/Pikachu.jpeg
perceptual_load/distractors/Spiderman.jpeg
perceptual_load/distractors/Spongebob.jpeg
perceptual_load/distractors/Superman.jpeg
perceptual_load/images/Consent.jpeg
perceptual_load/images/HighReminder.jpeg
perceptual_load/images/Instructions.jpeg
perceptual_load/images/LowReminder.jpeg
perceptual_load-0.0.9.dist-info/LICENSE
perceptual_load-0.0.9.dist-info/METADATA
perceptual_load-0.0.9.dist-info/WHEEL
perceptual_load-0.0.9.dist-info/top_level.txt
perceptual_load-0.0.9.dist-info/RECORD
